obj_det_metrics/__init__.py
obj_det_metrics/ap_map.py
obj_det_metrics/ingest.py
obj_det_metrics/utils.py
obj_det_metrics/variables.py
obj_det_metrics-0.2.1.dist-info/WHEEL
obj_det_metrics-0.2.1.dist-info/METADATA
obj_det_metrics-0.2.1.dist-info/RECORD
