Metadata-Version: 2.1
Name: obj-det-metrics
Version: 0.2.1
Summary: Simple package to compute metrics for object detection
Home-page: https://github.com/yxlee245/obj-det-metrics
Author: yxlee245
Author-email: yxlee245@gmail.com
Requires-Python: >=3.7,<4.0
Classifier: Programming Language :: Python :: 3
Classifier: Programming Language :: Python :: 3.7
Classifier: Programming Language :: Python :: 3.8
Classifier: Programming Language :: Python :: 3.9
Requires-Dist: numpy (>=1.18,<2.0)
Requires-Dist: pipe (>=1.6.0,<2.0.0)
